bw2python/__init__.py
bw2python/bwtypes.py
bw2python/client.py
bw2python/genPythonAllocations.py
bw2python/ponames.py
bw2python-0.3.dist-info/DESCRIPTION.rst
bw2python-0.3.dist-info/METADATA
bw2python-0.3.dist-info/RECORD
bw2python-0.3.dist-info/WHEEL
bw2python-0.3.dist-info/metadata.json
bw2python-0.3.dist-info/top_level.txt
