Metadata-Version: 2.0
Name: bw2python
Version: 0.3
Summary: Python bindings for Bosswave 2
Home-page: https://github.com/SoftwareDefinedBuildings/bw2python
Author: Jack Kolb
Author-email: jkolb@berkeley.edu
License: UNKNOWN
Platform: UNKNOWN
Requires-Dist: msgpack-python
